bncutils/__init__.py
bncutils/bnc_config.yml
bncutils/bnc_lib.py
bncutils/good_phrases
bncutils-0.0.5.dist-info/METADATA
bncutils-0.0.5.dist-info/WHEEL
bncutils-0.0.5.dist-info/licenses/LICENSE
bncutils-0.0.5.dist-info/RECORD
