Metadata-Version: 2.1
Name: bncutils
Version: 0.0.5
Summary: Utils for Bulls and Cows game project
Project-URL: Homepage, https://github.com/EugeneDlg/bncweb
Project-URL: Bug Tracker, https://github.com/EugeneDlg/bncweb
Author-email: eugenedg <orfray@gmail.com>
License-File: LICENSE
Classifier: License :: OSI Approved :: MIT License
Classifier: Operating System :: OS Independent
Classifier: Programming Language :: Python :: 3
Requires-Python: >=3.7
